pysui_gadgets/__init__.py
pysui_gadgets/version.py
pysui_gadgets/dsl/__init__.py
pysui_gadgets/dsl/dslgen.py
pysui_gadgets/dsl/dsl_run/__init__.py
pysui_gadgets/dsl/dsl_run/converter.py
pysui_gadgets/dsl/generators/__init__.py
pysui_gadgets/dsl/generators/package_gen.py
pysui_gadgets/dsl/ir/__init__.py
pysui_gadgets/dsl/ir/ir_types.py
pysui_gadgets/dsl/ir/modir.py
pysui_gadgets/dsl/templates/__init__.py
pysui_gadgets/dsl/templates/async_model.py
pysui_gadgets/dsl/templates/sync_model.py
pysui_gadgets/module/__init__.py
pysui_gadgets/module/module.py
pysui_gadgets/package/__init__.py
pysui_gadgets/package/package.py
pysui_gadgets/package/cmds/__init__.py
pysui_gadgets/package/cmds/funcs.py
pysui_gadgets/package/cmds/lists.py
pysui_gadgets/package/cmds/structs.py
pysui_gadgets/splay/__init__.py
pysui_gadgets/splay/splay.py
pysui_gadgets/to_one/__init__.py
pysui_gadgets/to_one/to_one.py
pysui_gadgets/utils/__init__.py
pysui_gadgets/utils/cmd_arg_validators.py
pysui_gadgets/utils/cmdlines.py
pysui_gadgets/utils/exec_helpers.py
pysui_gadgets/utils/filters.py
pysui_gadgets/vh/__init__.py
pysui_gadgets/vh/vh.py
pysui_gadgets-0.4.9.dist-info/LICENSE
pysui_gadgets-0.4.9.dist-info/METADATA
pysui_gadgets-0.4.9.dist-info/WHEEL
pysui_gadgets-0.4.9.dist-info/entry_points.txt
pysui_gadgets-0.4.9.dist-info/top_level.txt
pysui_gadgets-0.4.9.dist-info/RECORD
