Metadata-Version: 2.1
Name: pysui-gadgets
Version: 0.4.9
Summary: pysui (Python Sui Client SDK) additional tools
License: Apache-2.0
Project-URL: changelog, https://github.com/FrankC01/pysui_gadgets/issues
Project-URL: repository, https://github.com/FrankC01/pysui_gadgets
Project-URL: issues, https://github.com/FrankC01/pysui_gadgets/issues
Keywords: software development kit,sui,blockchain,utilities,pysui
Classifier: Development Status :: 4 - Beta
Classifier: Intended Audience :: Developers
Classifier: Topic :: Software Development
Classifier: Topic :: Software Development :: Libraries
Classifier: Programming Language :: Python
Classifier: Operating System :: OS Independent
Classifier: License :: OSI Approved :: Apache Software License
Classifier: Programming Language :: Python :: 3.10
Classifier: Programming Language :: Python :: 3.11
Classifier: Programming Language :: Python :: 3 :: Only
Requires-Python: >=3.10
License-File: LICENSE
Requires-Dist: pysui >=0.59.0
